[{"id":"yaoxing-fu-published-00081","sourceDocumentId":"yaoxing-fu","bookTitle":"藥性賦","chapter":"《藥性賦》第四章平性藥","pageStart":14,"pageEnd":14,"paragraphOrder":30,"originalTextSimplified":"五加皮坚筋骨以立行;柏子仁养心神而有益。","textTraditional":"五加皮堅筋骨以立行;柏子仁養心神而有益。","extractionMethod":"text-layer","extractionConfidence":1,"conversionProfile":"opencc-s2hk","conversionReviewed":true,"topics":[],"herbs":["柏子仁"],"formulas":[],"patterns":[],"organs":["心"],"qiBloodFluids":[],"coldHeat":[],"deficiencyExcess":[],"sourceFileName":"药性赋-古籍典藏-luckclub.pdf","sourceFileHash":"b3d75b55f942e9b954f2e9e17a816b469ea97a3fb1081fa68efca29e86715eb7","rightsStatus":"public-domain","publishable":true,"sourceStatus":"verified","reviewStatus":"approved","importedAt":"2026-07-20T00:00:00.000Z","toolVersion":"2.0.0","publicationRule":"排除導言、白話及現代啟示；保留賦文完整句段。"},{"id":"yaoxing-fu-published-00082","sourceDocumentId":"yaoxing-fu","bookTitle":"藥性賦","chapter":"《藥性賦》第四章平性藥","pageStart":14,"pageEnd":14,"paragraphOrder":31,"originalTextSimplified":"抑又闻安息香辟恶,且止心腹之痛;冬瓜仁醒脾,实为饮食之资。","textTraditional":"抑又聞安息香辟惡,且止心腹之痛;冬瓜仁醒脾,實為飲食之資。","extractionMethod":"text-layer","extractionConfidence":1,"conversionProfile":"opencc-s2hk","conversionReviewed":true,"topics":[],"herbs":["冬瓜"],"formulas":[],"patterns":[],"organs":["心","脾"],"qiBloodFluids":[],"coldHeat":[],"deficiencyExcess":["實"],"sourceFileName":"药性赋-古籍典藏-luckclub.pdf","sourceFileHash":"b3d75b55f942e9b954f2e9e17a816b469ea97a3fb1081fa68efca29e86715eb7","rightsStatus":"public-domain","publishable":true,"sourceStatus":"verified","reviewStatus":"approved","importedAt":"2026-07-20T00:00:00.000Z","toolVersion":"2.0.0","publicationRule":"排除導言、白話及現代啟示；保留賦文完整句段。"},{"id":"yaoxing-fu-published-00083","sourceDocumentId":"yaoxing-fu","bookTitle":"藥性賦","chapter":"《藥性賦》第四章平性藥","pageStart":14,"pageEnd":14,"paragraphOrder":32,"originalTextSimplified":"僵蚕治诸风之喉闭;百合恋肺痨之嗽萎。","textTraditional":"殭蠶治諸風之喉閉;百合戀肺癆之嗽萎。","extractionMethod":"text-layer","extractionConfidence":1,"conversionProfile":"opencc-s2hk","conversionReviewed":true,"topics":[],"herbs":["百合"],"formulas":[],"patterns":[],"organs":["肺"],"qiBloodFluids":[],"coldHeat":[],"deficiencyExcess":[],"sourceFileName":"药性赋-古籍典藏-luckclub.pdf","sourceFileHash":"b3d75b55f942e9b954f2e9e17a816b469ea97a3fb1081fa68efca29e86715eb7","rightsStatus":"public-domain","publishable":true,"sourceStatus":"verified","reviewStatus":"approved","importedAt":"2026-07-20T00:00:00.000Z","toolVersion":"2.0.0","publicationRule":"排除導言、白話及現代啟示；保留賦文完整句段。"},{"id":"yaoxing-fu-published-00084","sourceDocumentId":"yaoxing-fu","bookTitle":"藥性賦","chapter":"《藥性賦》第四章平性藥","pageStart":14,"pageEnd":14,"paragraphOrder":33,"originalTextSimplified":"赤小豆解热毒,疮肿宜用;枇杷叶下逆气,哕呕可医。","textTraditional":"赤小豆解熱毒,瘡腫宜用;枇杷葉下逆氣,噦嘔可醫。","extractionMethod":"text-layer","extractionConfidence":1,"conversionProfile":"opencc-s2hk","conversionReviewed":true,"topics":[],"herbs":["赤小豆"],"formulas":[],"patterns":[],"organs":[],"qiBloodFluids":["氣"],"coldHeat":["熱"],"deficiencyExcess":[],"sourceFileName":"药性赋-古籍典藏-luckclub.pdf","sourceFileHash":"b3d75b55f942e9b954f2e9e17a816b469ea97a3fb1081fa68efca29e86715eb7","rightsStatus":"public-domain","publishable":true,"sourceStatus":"verified","reviewStatus":"approved","importedAt":"2026-07-20T00:00:00.000Z","toolVersion":"2.0.0","publicationRule":"排除導言、白話及現代啟示；保留賦文完整句段。"},{"id":"yaoxing-fu-published-00085","sourceDocumentId":"yaoxing-fu","bookTitle":"藥性賦","chapter":"《藥性賦》第四章平性藥","pageStart":15,"pageEnd":15,"paragraphOrder":3,"originalTextSimplified":"连翘排疮脓与肿毒;石南叶利筋骨与毛皮。","textTraditional":"連翹排瘡膿與腫毒;石南葉利筋骨與毛皮。","extractionMethod":"text-layer","extractionConfidence":1,"conversionProfile":"opencc-s2hk","conversionReviewed":true,"topics":[],"herbs":["連翹"],"formulas":[],"patterns":[],"organs":[],"qiBloodFluids":[],"coldHeat":[],"deficiencyExcess":[],"sourceFileName":"药性赋-古籍典藏-luckclub.pdf","sourceFileHash":"b3d75b55f942e9b954f2e9e17a816b469ea97a3fb1081fa68efca29e86715eb7","rightsStatus":"public-domain","publishable":true,"sourceStatus":"verified","reviewStatus":"approved","importedAt":"2026-07-20T00:00:00.000Z","toolVersion":"2.0.0","publicationRule":"排除導言、白話及現代啟示；保留賦文完整句段。"},{"id":"yaoxing-fu-published-00086","sourceDocumentId":"yaoxing-fu","bookTitle":"藥性賦","chapter":"《藥性賦》第四章平性藥","pageStart":15,"pageEnd":15,"paragraphOrder":4,"originalTextSimplified":"谷芽养脾,阿魏除邪气而破积;紫河车补血,大枣和药性以开脾。","textTraditional":"谷芽養脾,阿魏除邪氣而破積;紫河車補血,大棗和藥性以開脾。","extractionMethod":"text-layer","extractionConfidence":1,"conversionProfile":"opencc-s2hk","conversionReviewed":true,"topics":[],"herbs":["大棗"],"formulas":[],"patterns":[],"organs":["脾"],"qiBloodFluids":["氣","血"],"coldHeat":[],"deficiencyExcess":[],"sourceFileName":"药性赋-古籍典藏-luckclub.pdf","sourceFileHash":"b3d75b55f942e9b954f2e9e17a816b469ea97a3fb1081fa68efca29e86715eb7","rightsStatus":"public-domain","publishable":true,"sourceStatus":"verified","reviewStatus":"approved","importedAt":"2026-07-20T00:00:00.000Z","toolVersion":"2.0.0","publicationRule":"排除導言、白話及現代啟示；保留賦文完整句段。"},{"id":"yaoxing-fu-published-00087","sourceDocumentId":"yaoxing-fu","bookTitle":"藥性賦","chapter":"《藥性賦》第四章平性藥","pageStart":15,"pageEnd":15,"paragraphOrder":5,"originalTextSimplified":"然而鳖甲治痨疟,兼破症葭;龟甲坚筋骨,更疗崩疾。","textTraditional":"然而鱉甲治癆瘧,兼破症葭;龜甲堅筋骨,更療崩疾。","extractionMethod":"text-layer","extractionConfidence":1,"conversionProfile":"opencc-s2hk","conversionReviewed":true,"topics":[],"herbs":[],"formulas":[],"patterns":[],"organs":[],"qiBloodFluids":[],"coldHeat":[],"deficiencyExcess":[],"sourceFileName":"药性赋-古籍典藏-luckclub.pdf","sourceFileHash":"b3d75b55f942e9b954f2e9e17a816b469ea97a3fb1081fa68efca29e86715eb7","rightsStatus":"public-domain","publishable":true,"sourceStatus":"verified","reviewStatus":"approved","importedAt":"2026-07-20T00:00:00.000Z","toolVersion":"2.0.0","publicationRule":"排除導言、白話及現代啟示；保留賦文完整句段。"},{"id":"yaoxing-fu-published-00088","sourceDocumentId":"yaoxing-fu","bookTitle":"藥性賦","chapter":"《藥性賦》第四章平性藥","pageStart":15,"pageEnd":15,"paragraphOrder":6,"originalTextSimplified":"乌梅主便血疟疾之用;竹沥治中风声音之失。","textTraditional":"烏梅主便血瘧疾之用;竹瀝治中風聲音之失。","extractionMethod":"text-layer","extractionConfidence":1,"conversionProfile":"opencc-s2hk","conversionReviewed":true,"topics":[],"herbs":["烏梅"],"formulas":[],"patterns":[],"organs":[],"qiBloodFluids":["血"],"coldHeat":[],"deficiencyExcess":[],"sourceFileName":"药性赋-古籍典藏-luckclub.pdf","sourceFileHash":"b3d75b55f942e9b954f2e9e17a816b469ea97a3fb1081fa68efca29e86715eb7","rightsStatus":"public-domain","publishable":true,"sourceStatus":"verified","reviewStatus":"approved","importedAt":"2026-07-20T00:00:00.000Z","toolVersion":"2.0.0","publicationRule":"排除導言、白話及現代啟示；保留賦文完整句段。"}]
